resilience_h8/__init__.py
resilience_h8/concurrency/__init__.py
resilience_h8/concurrency/async_task_manager.py
resilience_h8/concurrency/task_manager.py
resilience_h8/custom_types/__init__.py
resilience_h8/custom_types/common.py
resilience_h8/custom_types/resilience.py
resilience_h8/interfaces/__init__.py
resilience_h8/interfaces/concurrency.py
resilience_h8/interfaces/resilience.py
resilience_h8/interfaces/storage.py
resilience_h8/resilience/__init__.py
resilience_h8/resilience/bulkhead.py
resilience_h8/resilience/circuit_breaker.py
resilience_h8/resilience/decorators.py
resilience_h8/resilience/rate_limiter.py
resilience_h8/resilience/redis_circuit_breaker.py
resilience_h8/resilience/redis_rate_limiter.py
resilience_h8/resilience/retry.py
resilience_h8/storage/__init__.py
resilience_h8/storage/redis_backend.py
resilience_h8-0.2.0.dist-info/METADATA
resilience_h8-0.2.0.dist-info/WHEEL
resilience_h8-0.2.0.dist-info/top_level.txt
resilience_h8-0.2.0.dist-info/RECORD
