Metadata-Version: 2.4
Name: resilience_h8
Version: 0.2.0
Summary: Resilience patterns library (async) with circuit breaker, bulkhead, retry, and timeout patterns
Author-email: Harutyun Avetisyan <har.avetisyan2002@gmail.com>
License: MIT
Project-URL: Homepage, https://github.com/Harut8/resilience_h8
Project-URL: Bug Tracker, https://github.com/Harut8/resilience_h8/issues
Keywords: resilience,circuit-breaker,bulkhead,retry,timeout,async,microservices
Classifier: Development Status :: 4 - Beta
Classifier: Intended Audience :: Developers
Classifier: License :: OSI Approved :: MIT License
Classifier: Programming Language :: Python :: 3
Classifier: Programming Language :: Python :: 3.11
Classifier: Topic :: Software Development :: Libraries
Classifier: Topic :: Software Development :: Libraries :: Python Modules
Requires-Python: >=3.11
Requires-Dist: structlog>=23.1.0
Requires-Dist: typing_extensions>=4.5.0
Requires-Dist: httpx>=0.24.0
Requires-Dist: psutil>=7.0.0
Provides-Extra: redis
Requires-Dist: redis[hiredis]>=5.0.0; extra == "redis"
Provides-Extra: dev
Requires-Dist: ruff>=0.1.0; extra == "dev"
Requires-Dist: mypy>=1.3.0; extra == "dev"
Requires-Dist: pytest>=7.3.1; extra == "dev"
Requires-Dist: pytest-asyncio>=0.21.0; extra == "dev"
Requires-Dist: pytest-cov>=4.1.0; extra == "dev"
Requires-Dist: redis[hiredis]>=5.0.0; extra == "dev"
Provides-Extra: all
Requires-Dist: redis[hiredis]>=5.0.0; extra == "all"
